python_filmaffinity_fork/.gitignore
python_filmaffinity_fork/__init__.py
python_filmaffinity_fork/__meta__.py
python_filmaffinity_fork/cache-film-affinity.sqlite
python_filmaffinity_fork/client.py
python_filmaffinity_fork/config.py
python_filmaffinity_fork/exceptions.py
python_filmaffinity_fork/pages/__init__.py
python_filmaffinity_fork/pages/detail.py
python_filmaffinity_fork/pages/images.py
python_filmaffinity_fork/pages/page.py
python_filmaffinity_fork/pages/search.py
python_filmaffinity_fork/pages/top.py
python_filmaffinity_fork/pages/top_service.py
python_filmaffinity_fork/proxies.py
python_filmaffinity_fork-0.0.20.dist-info/AUTHORS.rst
python_filmaffinity_fork-0.0.20.dist-info/LICENSE.rst
python_filmaffinity_fork-0.0.20.dist-info/METADATA
python_filmaffinity_fork-0.0.20.dist-info/WHEEL
python_filmaffinity_fork-0.0.20.dist-info/RECORD
