Metadata-Version: 2.1
Name: python-filmaffinity-fork
Version: 0.0.20
Summary: Simple python scraping for the FilmAffinity.
Author: Your Name
Author-email: you@example.com
Requires-Python: >=3.10,<3.13
Classifier: Programming Language :: Python :: 3
Classifier: Programming Language :: Python :: 3.10
Classifier: Programming Language :: Python :: 3.11
Classifier: Programming Language :: Python :: 3.12
Requires-Dist: aarpy (>=0.1,<0.2)
Requires-Dist: appdirs (>=1.4.4,<2.0.0)
Requires-Dist: astroid (>=3.1.0,<4.0.0)
Requires-Dist: backports-shutil-get-terminal-size (>=1.0.0,<2.0.0)
Requires-Dist: beautifulsoup4 (>=4.12.3,<5.0.0)
Requires-Dist: bs4 (>=0.0.2,<0.0.3)
Requires-Dist: certifi (>=2024.2.2,<2025.0.0)
Requires-Dist: configparser (>=7.0.0,<8.0.0)
Requires-Dist: decorator (>=5.1.1,<6.0.0)
Requires-Dist: enum34 (>=1.1.10,<2.0.0)
Requires-Dist: ipython (>=8.24.0,<9.0.0)
Requires-Dist: ipython-genutils (>=0.2.0,<0.3.0)
Requires-Dist: isort (>=5.13.2,<6.0.0)
Requires-Dist: lazy-object-proxy (>=1.10.0,<2.0.0)
Requires-Dist: mccabe (>=0.7.0,<0.8.0)
Requires-Dist: packaging (>=24.0,<25.0)
Requires-Dist: pathlib2 (>=2.3.7.post1,<3.0.0)
Requires-Dist: pep8 (>=1.7.1,<2.0.0)
Requires-Dist: pexpect (>=4.9.0,<5.0.0)
Requires-Dist: pickleshare (>=0.7.5,<0.8.0)
Requires-Dist: prompt-toolkit (>=3.0.43,<4.0.0)
Requires-Dist: ptyprocess (>=0.7.0,<0.8.0)
Requires-Dist: pygments (>=2.18.0,<3.0.0)
Requires-Dist: pylint (>=3.1.0,<4.0.0)
Requires-Dist: pyparsing (>=3.1.2,<4.0.0)
Requires-Dist: pytest (>=8.2.0,<9.0.0)
Requires-Dist: requests-cache (>=1.2.0,<2.0.0)
Requires-Dist: requests[security] (>=2.31.0,<3.0.0)
Requires-Dist: scandir (>=1.10.0,<2.0.0)
Requires-Dist: setuptools (>=69.5.1,<70.0.0)
Requires-Dist: simplegeneric (>=0.8.1,<0.9.0)
Requires-Dist: singledispatch (>=4.1.0,<5.0.0)
Requires-Dist: traitlets (>=5.14.3,<6.0.0)
Requires-Dist: user-agent (>=0.1.10,<0.2.0)
Requires-Dist: wcwidth (>=0.2.13,<0.3.0)
Requires-Dist: wrapt (>=1.16.0,<2.0.0)
